{"id":"component2.html","dependencies":[],"generated":{"html":"<!DOCTYPE html>\r\n<html lang=\"en\">\r\n<head>\r\n    <meta charset=\"UTF-8\">\r\n    <meta http-equiv=\"X-UA-Compatible\" content=\"IE=edge\">\r\n    <meta name=\"viewport\" content=\"width=device-width, initial-scale=1.0\">\r\n    <title>组件的使用技巧</title>\r\n</head>\r\n<body>\r\n    <div id=\"app\">\r\n        <button @click=\"plus\">{{count}}</button>\r\n        <button @click=\"plus\">{{count}}</button>\r\n        <hr>\r\n        <btn-component></btn-component>\r\n        <btn-component></btn-component>\r\n\r\n        \r\n    </div>\r\n    <script src=\"https://cdn.jsdelivr.net/npm/vue@2/dist/vue.js\"></script>\r\n    <script>\r\n        //推荐使用小写字母加-进行命名 child,my-component\r\n        //template必须被一个dom元素包括，也可以嵌套\r\n        //组件的定义中。除了template之外的其他选项 data,computed,methods\r\n        //data必须是一个方法\r\n\r\n        var app=new Vue({\r\n            el:\"#app\",\r\n            data:{\r\n                count:1\r\n            },\r\n            components:{\r\n                'app-component':{\r\n                    template:'<div>我是app局部组件</div>'\r\n                },\r\n                'btn-component':{\r\n                    template:'<button @click=\"count++\">{{count}}</button>',\r\n                    data:function(){\r\n                        return{\r\n                            count:0\r\n                        }\r\n                    }\r\n                }\r\n            },\r\n            methods:{\r\n                plus:function(){\r\n                    this.count++;\r\n                }\r\n            }\r\n\r\n        })\r\n       \r\n    </script>\r\n    \r\n</body>\r\n</html>"},"hash":"cabaa84178ab342ed2d55198d90e8d9f","cacheData":{}}